pyskani-0.2.0.dist-info/METADATA
pyskani-0.2.0.dist-info/WHEEL
pyskani-0.2.0.dist-info/license_files/COPYING
pyskani/_skani.pyi
pyskani/tests/test_ani.py
pyskani/tests/test_database.py
pyskani/tests/__init__.py
pyskani/tests/unittest.rs
pyskani/tests/e.coli-K12.fasta.gz
pyskani/tests/e.coli-EC590.fasta.gz
pyskani/tests/fasta.py
pyskani/__init__.py
pyskani/_skani/lib.rs
pyskani/_skani/build.rs
pyskani/_skani/sketch.rs
pyskani/_skani/hit.rs
pyskani/_skani/utils.rs
pyskani/py.typed
pyskani/_skani.cpython-311-darwin.so
pyskani-0.2.0.dist-info/RECORD
