Metadata-Version: 2.1
Name: pyskani
Version: 0.2.0
Classifier: Development Status :: 3 - Alpha
Classifier: Intended Audience :: Developers
Classifier: Intended Audience :: Science/Research
Classifier: License :: OSI Approved :: MIT License
Classifier: Operating System :: OS Independent
Classifier: Programming Language :: Rust
Classifier: Programming Language :: Python :: 3.7
Classifier: Programming Language :: Python :: 3.8
Classifier: Programming Language :: Python :: 3.9
Classifier: Programming Language :: Python :: 3.10
Classifier: Programming Language :: Python :: 3.11
Classifier: Programming Language :: Python :: 3.12
Classifier: Programming Language :: Python :: 3.13
Classifier: Programming Language :: Python :: Implementation :: CPython
Classifier: Programming Language :: Python :: Implementation :: PyPy
Classifier: Topic :: Scientific/Engineering :: Bio-Informatics
Classifier: Topic :: Scientific/Engineering :: Medical Science Apps.
Classifier: Topic :: Software Development :: Libraries :: Python Modules
Classifier: Typing :: Typed
License-File: COPYING
Summary: PyO3 bindings and Python interface to skani, a method for fast fast genomic identity calculation using sparse chaining.
Keywords: bioinformatics,genomics,average,nucleotide,identity
Home-Page: https://github.com/althonos/pyskani/
Author: Martin Larralde <martin.larralde@embl.de>
Author-email: Martin Larralde <martin.larralde@embl.de>
License: MIT
Requires-Python: >=3.7
Project-URL: Homepage, https://github.com/althonos/pyskani/
Project-URL: Documentation, https://pyskani.readthedocs.io
Project-URL: Bug Tracker, https://github.com/althonos/pyskani/issues
Project-URL: Changelog, https://github.com/althonos/pyskani/blob/master/CHANGELOG.md
Project-URL: Builds, https://github.com/althonos/pyskani/actions/
Project-URL: PyPI, https://pypi.org/project/pyskani
